turbine/__init__.py
turbine/cli.py
turbine/src/__init__.py
turbine/src/function_deploy/Dockerfile
turbine/src/function_deploy/__init__.py
turbine/src/function_deploy/requirements.txt
turbine/src/function_deploy/function_app/README.md
turbine/src/function_deploy/function_app/__init__.py
turbine/src/function_deploy/function_app/function_server.py
turbine/src/function_deploy/function_app/record.py
turbine/src/function_deploy/function_app/proto_gen/__init__.py
turbine/src/function_deploy/function_app/proto_gen/service_pb2.py
turbine/src/function_deploy/function_app/proto_gen/service_pb2.pyi
turbine/src/function_deploy/function_app/proto_gen/service_pb2_grpc.py
turbine/src/turbine_app/__init__.py
turbine/src/turbine_app/app.py
turbine/src/turbine_app/client.py
turbine/src/turbine_app/resource.py
turbine/src/turbine_app/types.py
turbine/src/turbine_app/utils.py
turbine/src/turbine_app/proto_gen/__init__.py
turbine/src/turbine_app/proto_gen/turbine_pb2.py
turbine/src/turbine_app/proto_gen/turbine_pb2_grpc.py
turbine/src/turbine_app/proto_gen/validate_pb2.py
turbine/src/turbine_app/proto_gen/validate_pb2_grpc.py
turbine_py-2.1.4.dist-info/LICENSE.md
turbine_py-2.1.4.dist-info/METADATA
turbine_py-2.1.4.dist-info/WHEEL
turbine_py-2.1.4.dist-info/entry_points.txt
turbine_py-2.1.4.dist-info/top_level.txt
turbine_py-2.1.4.dist-info/RECORD
