Metadata-Version: 2.1
Name: turbine-py
Version: 2.1.4
Summary: Meroxa Turbine data application framework
Home-page: https://meroxa.io/
Author: Eric Cheatham
Author-email: eric@meroxa.io
License: MIT
Project-URL: Source Code, https://github.com/meroxa/turbine-py/
Project-URL: Issue Tracker, https://github.com/meroxa/turbine-py/issues
Classifier: Programming Language :: Python
Classifier: License :: OSI Approved :: MIT License
Classifier: Operating System :: OS Independent
Requires-Python: >=3.9
License-File: LICENSE.md
Requires-Dist: aiohttp >=3.8
Requires-Dist: grpcio >=1.44.0
Requires-Dist: google >=3.0.0
Requires-Dist: google-api-python-client >=2.86.0
Requires-Dist: grpcio-tools >=1.44.0
Requires-Dist: protobuf >=3.20.0
Requires-Dist: grpcio-reflection >=1.44.0
Requires-Dist: grpcio-health-checking >=1.44.0
